protoc_gen_openapiv2/options/__init__.py
protoc_gen_openapiv2/options/annotations_pb2.py
protoc_gen_openapiv2/options/openapiv2_pb2.py
protoc_gen_openapiv2-0.0.1.dist-info/LICENSE
protoc_gen_openapiv2-0.0.1.dist-info/METADATA
protoc_gen_openapiv2-0.0.1.dist-info/WHEEL
protoc_gen_openapiv2-0.0.1.dist-info/top_level.txt
protoc_gen_openapiv2-0.0.1.dist-info/RECORD
