Metadata-Version: 2.1
Name: protoc-gen-openapiv2
Version: 0.0.1
Summary: Provides the missing pieces for gRPC Gateway.
Home-page: https://github.com/unionai-oss/protoc-gen-openapiv2
Author: eapolinario
Author-email: eapolinario@union.ai
Project-URL: Bug Tracker, https://github.com/unionai-oss/protoc-gen-openapiv2/issues
Classifier: Programming Language :: Python :: 3
Classifier: License :: OSI Approved :: BSD License
Classifier: Operating System :: OS Independent
Requires-Python: >=3.6
License-File: LICENSE
